Metadata-Version: 2.4
Name: bepasty
Version: 1.2.2
Summary: a binary pastebin / file upload service
Author: The Bepasty Team (see AUTHORS file)
Maintainer-email: Thomas Waldmann <tw@waldmann-edv.de>
License: BSD 2-clause
Project-URL: Homepage, https://github.com/bepasty/bepasty-server/
Project-URL: Documentation, https://bepasty-server.readthedocs.org/
Project-URL: Changelog, https://github.com/bepasty/bepasty-server/blob/master/CHANGES.rst
Keywords: text,image,audio,video,binary,pastebin,upload,download,service,wsgi,flask
Classifier: Development Status :: 5 - Production/Stable
Classifier: Environment :: Web Environment
Classifier: License :: OSI Approved :: BSD License
Classifier: Operating System :: OS Independent
Classifier: Framework :: Flask
Classifier: Programming Language :: Python
Classifier: Programming Language :: Python :: 3
Classifier: Programming Language :: Python :: 3.8
Classifier: Programming Language :: Python :: 3.9
Classifier: Programming Language :: Python :: 3.10
Classifier: Programming Language :: Python :: 3.11
Classifier: Programming Language :: Python :: 3.12
Classifier: Programming Language :: Python :: 3.13
Requires-Python: >=3.8
License-File: LICENSE
License-File: AUTHORS
Requires-Dist: werkzeug
Requires-Dist: Flask
Requires-Dist: markupsafe
Requires-Dist: Pygments>=2.12.0
Requires-Dist: xstatic<2.0.0
Requires-Dist: XStatic-asciinema-player<=2.6.1.1
Requires-Dist: xstatic-bootbox<=5.5.1.1,>=5.4.0
Requires-Dist: xstatic-bootstrap<=4.5.3.1,>=4.0.0.0
Requires-Dist: xstatic-font-awesome<=4.7.0.0
Requires-Dist: xstatic-jquery<=3.5.1.1
Requires-Dist: xstatic-jquery-ui<=1.13.0.1
Requires-Dist: xstatic-jquery-file-upload<=10.31.0.1
Requires-Dist: xstatic-pygments<=2.9.0.1
Provides-Extra: magic
Requires-Dist: python-magic; extra == "magic"
Provides-Extra: pillow
Requires-Dist: Pillow; extra == "pillow"
Dynamic: license-file
